woffu_client/__init__.py
woffu_client/cli.py
woffu_client/stdrequests_session.py
woffu_client/woffu_api_client.py
woffu_client-0.1.6.dist-info/licenses/LICENSE
woffu_client-0.1.6.dist-info/METADATA
woffu_client-0.1.6.dist-info/WHEEL
woffu_client-0.1.6.dist-info/entry_points.txt
woffu_client-0.1.6.dist-info/top_level.txt
woffu_client-0.1.6.dist-info/RECORD
