Metadata-Version: 2.4
Name: woffu_client
Version: 0.1.6
Summary: Woffu API client with access to several endpoints.
Author-email: Marc Palacín Marfil <marc.palacin.marfil@gmail.com>
License: MIT
Project-URL: Homepage, https://github.com/ProtossGP32/woffu-client
Requires-Python: <3.14,>=3.10
License-File: LICENSE
Requires-Dist: tzlocal==5.3.1
Requires-Dist: tzdata==2025.2
Provides-Extra: dev
Requires-Dist: pytest==8.1.1; extra == "dev"
Requires-Dist: pytest-cov==5.0.0; extra == "dev"
Requires-Dist: pre-commit==4.3.0; extra == "dev"
Dynamic: license-file
